{
  "meta": {
    "id": "epistle-to-diognetus",
    "author": "Epistle to Diognetus",
    "tradition": [],
    "tradition_notes": null,
    "license": "public-domain",
    "schema_type": "church_fathers",
    "schema_version": "2.1.0",
    "provenance": {
      "source_url": "https://github.com/HistoricalChristianFaith/Commentaries-Database",
      "source_format": "TOML",
      "source_edition": "HistoricalChristianFaith/Commentaries-Database (public domain)",
      "download_date": "2026-03-28",
      "source_hash": "sha256:910764c8fab68db9f71633966ab0aee3dc87c46a7d706e7e974e0109ef913d7c",
      "processing_method": "automated",
      "processing_script_version": "build/parsers/church_fathers.py@v1.0.0",
      "processing_date": "2026-03-28",
      "notes": "Processed 1 quotes from 2 verse files. Source: HistoricalChristianFaith/Commentaries-Database. License: PUBLIC DOMAIN."
    }
  },
  "data": [
    {
      "entry_id": "epistle-to-diognetus.John.17.11.letter-to-diognetus-6",
      "author": "Epistle to Diognetus",
      "anchor_ref": {
        "raw": "John 17:11",
        "osis": [
          "John.17.11"
        ]
      },
      "quote": "In a word, what the soul is to the body, Christians are to the world. The soul is dispersed through all the members of the body, and Christians throughout the cities of the world. The soul dwells in the body but is not of the body. Likewise, Christians dwell in the world but are not of the world. The soul, which is invisible, is confined in the body, which is visible. In the same way, Christians are recognized as being in the world, and yet their religion remains invisible. The flesh hates the soul and wages war against it, even though it has suffered no wrong, because it is hindered from indulging in its pleasures. Similarly, the world also hates the Christians, even though it has suffered no wrong, because they set themselves against its pleasures. The soul loves the flesh that hates it and its members, and Christians love those who hate them. The soul is enclosed in the body, but it holds the body together. And though Christians are detained in the world as if in a prison, they in fact hold the world together. The soul, which is immortal, lives in a mortal dwelling. In a similar way, Christians live as strangers amid perishable things, while waiting for the imperishable in heaven. The soul, when poorly treated with respect to food and drink, becomes all the better. And so Christians when punished daily increase more and more. Such is the important position to which God has appointed them, and it is not right for them to decline it.",
      "source_title": "LETTER TO DIOGNETUS 6",
      "source_url": "",
      "attribution_note": null,
      "context": null,
      "word_count": 261
    }
  ]
}
